fastapi_security_cookie/__init__.py
fastapi_security_cookie/cookie.py
fastapi_security_cookie/enums.py
fastapi_security_cookie/exceptions.py
fastapi_security_cookie/schemas.py
fastapi_security_cookie-0.1.4.dist-info/LICENSE
fastapi_security_cookie-0.1.4.dist-info/METADATA
fastapi_security_cookie-0.1.4.dist-info/WHEEL
fastapi_security_cookie-0.1.4.dist-info/RECORD
